{"name":"fileDoesNotExist","id":"com.studentapp.junit.sstudentsidinfo.Serenityinfo:fileDoesNotExist","testCaseName":"com.studentapp.junit.sstudentsidinfo.Serenityinfo","userStory":{"id":"com.studentapp.junit.sstudentsidinfo.Serenityinfo","storyName":"Serenityinfo","storyClassName":"com.studentapp.junit.sstudentsidinfo.Serenityinfo","path":"sstudentsidinfo","type":"story"},"featureTag":{"name":"Serenityinfo","type":"story"},"title":"File does not exist","tags":[{"name":"Sstudentsidinfo","type":"feature"},{"name":"Sstudentsidinfo/Serenityinfo","type":"story"}],"startTime":"2021-06-19T08:47:22.140+05:30[Asia/Calcutta]","duration":1136,"testFailureCause":{"errorType":"java.io.FileNotFoundException","message":"D:\\file.txt (The system cannot find the file specified)","stackTrace":[{"declaringClass":"com.studentapp.junit.sstudentsidinfo.Serenityinfo","methodName":"fileDoesNotExist","fileName":"Serenityinfo.java","lineNumber":65}]},"testFailureClassname":"java.io.FileNotFoundException","testFailureMessage":"D:\\file.txt (The system cannot find the file specified)","testFailureSummary":"ERROR;java.io.FileNotFoundException;D:\\file.txt (The system cannot find the file specified);Serenityinfo.java","projectKey":"","annotatedResult":"ERROR","manual":false,"testSource":"JUnit","result":"ERROR"}